interop_router/__init__.py
interop_router/anthropic_provider.py
interop_router/gemini_provider.py
interop_router/openai_provider.py
interop_router/py.typed
interop_router/router.py
interop_router/types.py
interop_router-0.1.4.dist-info/WHEEL
interop_router-0.1.4.dist-info/METADATA
interop_router-0.1.4.dist-info/RECORD
