Metadata-Version: 2.3
Name: interop-router
Version: 0.1.4
Summary: Interoperate between AI providers using the OpenAI Responses API as a common interface.
Author: David Koleczek
Author-email: David Koleczek <45405824+DavidKoleczek@users.noreply.github.com>
Requires-Dist: anthropic[aiohttp]>=0.76,<1.0
Requires-Dist: google-genai[aiohttp]>=1.60,<2.0
Requires-Dist: openai[aiohttp]>=2.15,<3.0
Requires-Dist: pydantic>=2.12,<3.0
Requires-Python: >=3.11
